{
    "message": {
        "input": {
            "population": [
                {
                    "name": "User_load",
                    "count": 1,
                    "attributes": {
                        "energy_rating": "A/B/C",
                        "number_habitable_rooms": "3+",
                        "urbanity": "Urban",
                        "property_type_1": "House",
                        "property_type_2": "Terraced",
                        "is_mains_gas": "Has Mains Gas",
                        "lct": [
                            "Has No LCTs"
                        ]
                    }
                }
            ],
            "day_of_week": "Saturday",
            "month_of_year": "January"
        },
        "results": [
            {
                "name": "User_load",
                "day_of_week": "Saturday",
                "month_of_year": "January",
                "query_str": "month_of_year == 8 and day_of_week == 4 and (has_heat_pump == 1 and has_home_battery == 1 and has_solar_pv == 1 and has_electric_hot_water == 1 and has_electric_radiator == 1 and num_vehicles_charged_at_home not in [1, 3]) and has_solar_pv == 1 and num_vehicles_charged_at_home not in [3, 1] and has_heat_pump == 1 and energy_rating in [1] and number_habitable_rooms in [1] and urbanity in [1] and property_type_1 in [1] and property_type_2 in [4] and is_mains_gas == 1",
                "count": 1,
                "kwh": [
                    [
                        "0.9511",
                        "0.9163",
                        "0.8692",
                        "0.8499",
                        "0.8324",
                        "0.83",
                        "0.8212",
                        "0.7826",
                        "0.7823",
                        "0.7548",
                        "0.7575",
                        "0.6969",
                        "0.5591",
                        "0.4966",
                        "0.4637",
                        "0.4434",
                        "0.4086",
                        "0.4653",
                        "0.5466",
                        "0.4292",
                        "0.4472",
                        "0.5238",
                        "0.5328",
                        "0.6097",
                        "0.5589",
                        "0.6128",
                        "0.4809",
                        "0.562",
                        "0.5105",
                        "0.4906",
                        "0.4516",
                        "0.4396",
                        "0.4496",
                        "0.448",
                        "0.4441",
                        "0.4702",
                        "0.5512",
                        "0.4199",
                        "0.0",
                        "0.9018",
                        "2.8963",
                        "3.6704",
                        "3.5204",
                        "3.0157",
                        "2.6947",
                        "1.7017",
                        "0.7788",
                        "0.8869"
                    ]
                ]
            }
        ]
    }
}